Metadata-Version: 2.1
Name: warp-dggs
Version: 0.2.0
Summary: WARP Discrete Global Grids Package
Home-page: https://www.geo.tuwien.ac.at/
Author: TU Wien
Author-email: remote.sensing@geo.tuwien.ac.at
License: mit
Project-URL: Documentation, https://pyscaffold.org/
Platform: any
Classifier: Development Status :: 4 - Beta
Classifier: Programming Language :: Python
Requires-Python: >=3.6
Provides-Extra: testing
